8 bit Counter/top.v
`timescale 1ns/1ps

module top(
    output [7:0] q,
    input hw_clk,
    input rst
);
    wire c_out;

    // Instantiate the clock divider
    clockdivider clk_div(
        .c_out(c_out),
        .clk(hw_clk),
        .rst(rst)
    );

    // Instantiate the counter
    counter cnt(
        .q(q),
        .clk(c_out),
        .rst(rst)
    );

endmodule

module clockdivider(
    output reg c_out,
    input clk,
    input rst
);
    reg [23:0] count;  // Reduced bit size to fit the clock divider calculation

    always @(posedge clk or negedge rst) begin
        if (!rst) begin
            c_out <= 0;
            count <= 0;
        end else if (count == 5999999) begin  // (12 MHz / 2 Hz) / 2 = 6 million
            count <= 0;
            c_out <= ~c_out;
        end else begin
            count <= count + 1;
        end
    end
endmodule

module counter(
    output reg [7:0] q,
    input clk,
    input rst
);
    always @(posedge clk or negedge rst) begin
        if (!rst) begin
            q <= 8'b00000000;
        end else begin
            q <= q + 1;
        end
    end 
endmodule

8 bit Counter/top_tb.v
`timescale 1ns/1ps

module top_tb;

    reg hw_clk;
    reg rst;
    wire [7:0] q;

    // Instantiate the DUT (Device Under Test)
    top uut (
        .q(q),
        .hw_clk(hw_clk),
        .rst(rst)
    );

    // Generate a 12 MHz clock (Period = 83.33 ns)
    always #41.67 hw_clk = ~hw_clk;

    initial begin
        // Initialize signals
        hw_clk = 0;
        rst = 0;

        // Apply reset
        #100;
        rst = 1;

        // Run simulation for some time
        #1000000;  // 1 ms

        $finish;
    end

    // Dump waveforms for viewing in GTKWave
    initial begin
        $dumpfile("top_tb.vcd");
        $dumpvars(0, top_tb);
    end

endmodule

8 bit Counter/top_tb.vcd
$date
	Mon Mar 17 10:21:05 2025
$end
$version
	Icarus Verilog
$end
$timescale
	1ps
$end
$scope module top_tb $end
$var wire 8 ! q [7:0] $end
$var reg 1 " hw_clk $end
$var reg 1 # rst $end
$scope module uut $end
$var wire 1 " hw_clk $end
$var wire 1 # rst $end
$var wire 8 $ q [7:0] $end
$var wire 1 % c_out $end
$scope module clk_div $end
$var wire 1 " clk $end
$var wire 1 # rst $end
$var reg 1 % c_out $end
$var reg 24 & count [23:0] $end
$upscope $end
$scope module cnt $end
$var wire 1 % clk $end
$var wire 1 # rst $end
$var reg 8 ' q [7:0] $end
$upscope $end
$upscope $end
$upscope $end
$enddefinitions $end
$comment Show the parameter values. $end
$dumpall
$end
#0
$dumpvars
b0 '
b0 &
0%
b0 $
0#
0"
b0 !
$end
#41670
1"
#83340
0"
#100000
1#
#125010
b1 &
1"
#166680
0"
#208350
b10 &
1"
#250020
0"
#291690
b11 &
1"
#333360
0"
#375030
b100 &
1"
#416700
0"
#458370
b101 &
1"
#500040
0"
#541710
b110 &
1"
#583380
0"
#625050
b111 &
1"
#666720
0"
#708390
b1000 &
1"
#750060
0"
#791730
b1001 &
1"
#833400
0"
#875070
b1010 &
1"
#916740
0"
#958410
b1011 &
1"
#1000080
0"
#1041750
b1100 &
1"
#1083420
0"
#1125090
b1101 &
1"
#1166760
0"
#1208430
b1110 &
1"
#1250100
0"
#1291770
b1111 &
1"
#1333440
0"
#1375110
b10000 &
1"
#1416780
0"
#1458450
b10001 &
1"
#1500120
0"
#1541790
b10010 &
1"
#1583460
0"
#1625130
b10011 &
1"
#1666800
0"
#1708470
b10100 &
1"
#1750140
0"
#1791810
b10101 &
1"
#1833480
0"
#1875150
b10110 &
1"
#1916820
0"
#1958490
b10111 &
1"
#2000160
0"
#2041830
b11000 &
1"
#2083500
0"
#2125170
b11001 &
1"
#2166840
0"
#2208510
b11010 &
1"
#2250180
0"
#2291850
b11011 &
1"
#2333520
0"
#2375190
b11100 &
1"
#2416860
0"
#2458530
b11101 &
1"
#2500200
0"
#2541870
b11110 &
1"
#2583540
0"
#2625210
b11111 &
1"
#2666880
0"
#2708550
b100000 &
1"
#2750220
0"
#2791890
b100001 &
1"
#2833560
0"
#2875230
b100010 &
1"
#2916900
0"
#2958570
b100011 &
1"
#3000240
0"
#3041910
b100100 &
1"
#3083580
0"
#3125250
b100101 &
1"
#3166920
0"
#3208590
b100110 &
1"
#3250260
0"
#3291930
b100111 &
1"
#3333600
0"
#3375270
b101000 &
1"
#3416940
0"
#3458610
b101001 &
1"
#3500280
0"
#3541950
b101010 &
1"
#3583620
0"
#3625290
b101011 &
1"
#3666960
0"
#3708630
b101100 &
1"
#3750300
0"
#3791970
b101101 &
1"
#3833640
0"
#3875310
b101110 &
1"
#3916980
0"
#3958650
b101111 &
1"
#4000320
0"
#4041990
b110000 &
1"
#4083660
0"
#4125330
b110001 &
1"
#4167000
0"
#4208670
b110010 &
1"
#4250340
0"
#4292010
b110011 &
1"
#4333680
0"
#4375350
b110100 &
1"
#4417020
0"
#4458690
b110101 &
1"
#4500360
0"
#4542030
b110110 &
1"
#4583700
0"
#4625370
b110111 &
1"
#4667040
0"
#4708710
b111000 &
1"
#4750380
0"
#4792050
b111001 &
1"
#4833720
0"
#4875390
b111010 &
1"
#4917060
0"
#4958730
b111011 &
1"
#5000400
0"
#5042070
b111100 &
1"
#5083740
0"
#5125410
b111101 &
1"
#5167080
0"
#5208750
b111110 &
1"
#5250420
0"
#5292090
b111111 &
1"
#5333760
0"
#5375430
b1000000 &
1"
#5417100
0"
#5458770
b1000001 &
1"
#5500440
0"
#5542110
b1000010 &
1"
#5583780
0"
#5625450
b1000011 &
1"
#5667120
0"
#5708790
b1000100 &
1"
#5750460
0"
#5792130
b1000101 &
1"
#5833800
0"
#5875470
b1000110 &
1"
#5917140
0"
#5958810
b1000111 &
1"
#6000480
0"
#6042150
b1001000 &
1"
#6083820
0"
#6125490
b1001001 &
1"
#6167160
0"
#6208830
b1001010 &
1"
#6250500
0"
#6292170
b1001011 &
1"
#6333840
0"
#6375510
b1001100 &
1"
#6417180
0"
#6458850
b1001101 &
1"
#6500520
0"
#6542190
b1001110 &
1"
#6583860
0"
#6625530
b1001111 &
1"
#6667200
0"
#6708870
b1010000 &
1"
#6750540
0"
#6792210
b1010001 &
1"
#6833880
0"
#6875550
b1010010 &
1"
#6917220
0"
#6958890
b1010011 &
1"
#7000560
0"
#7042230
b1010100 &
1"
#7083900
0"
#7125570
b1010101 &
1"
#7167240
0"
#7208910
b1010110 &
1"
#7250580
0"
#7292250
b1010111 &
1"
#7333920
0"
#7375590
b1011000 &
1"
#7417260
0"
#7458930
b1011001 &
1"
#7500600
0"
#7542270
b1011010 &
1"
#7583940
0"
#7625610
b1011011 &
1"
#7667280
0"
#7708950
b1011100 &
1"
#7750620
0"
#7792290
b1011101 &
1"
#7833960
0"
#7875630
b1011110 &
1"
#7917300
0"
#7958970
b1011111 &
1"
#8000640
0"
#8042310
b1100000 &
1"
#8083980
0"
#8125650
b1100001 &
1"
#8167320
0"
#8208990
b1100010 &
1"
#8250660
0"
#8292330
b1100011 &
1"
#8334000
0"
#8375670
b1100100 &
1"
#8417340
0"
#8459010
b1100101 &
1"
#8500680
0"
#8542350
b1100110 &
1"
#8584020
0"
#8625690
b1100111 &
1"
#8667360
0"
#8709030
b1101000 &
1"
#8750700
0"
#8792370
b1101001 &
1"
#8834040
0"
#8875710
b1101010 &
1"
#8917380
0"
#8959050
b1101011 &
1"
#9000720
0"
#9042390
b1101100 &
1"
#9084060
0"
#9125730
b1101101 &
1"
#9167400
0"
#9209070
b1101110 &
1"
#9250740
0"
#9292410
b1101111 &
1"
#9334080
0"
#9375750
b1110000 &
1"
#9417420
0"
#9459090
b1110001 &
1"
#9500760
0"
#9542430
b1110010 &
1"
#9584100
0"
#9625770
b1110011 &
1"
#9667440
0"
#9709110
b1110100 &
1"
#9750780
0"
#9792450
b1110101 &
1"
#9834120
0"
#9875790
b1110110 &
1"
#9917460
0"
#9959130
b1110111 &
1"
#10000800
0"
#10042470
b1111000 &
1"
#10084140
0"
#10125810
b1111001 &
1"
#10167480
0"
#10209150
b1111010 &
1"
#10250820
0"
#10292490
b1111011 &
1"
#10334160
0"
#10375830
b1111100 &
1"
#10417500
0"
#10459170
b1111101 &
1"
#10500840
0"
#10542510
b1111110 &
1"
#10584180
0"
#10625850
b1111111 &
1"
#10667520
0"
#10709190
b10000000 &
1"
#10750860
0"
#10792530
b10000001 &
1"
#10834200
0"
#10875870
b10000010 &
1"
#10917540
0"
#10959210
b10000011 &
1"
#11000880
0"
#11042550
b10000100 &
1"
#11084220
0"
#11125890
b10000101 &
1"
#11167560
0"
#11209230
b10000110 &
1"
#11250900
0"
#11292570
b10000111 &
1"
#11334240
0"
#11375910
b10001000 &
1"
#11417580
0"
#11459250
b10001001 &
1"
#11500920
0"
#11542590
b10001010 &
1"
#11584260
0"
#11625930
b10001011 &
1"
#11667600
0"
#11709270
b10001100 &
1"
#11750940
0"
#11792610
b10001101 &
1"
#11834280
0"
#11875950
b10001110 &
1"
#11917620
0"
#11959290
b10001111 &
1"
#12000960
0"
#12042630
b10010000 &
1"
#12084300
0"
#12125970
b10010001 &
1"
#12167640
0"
#12209310
b10010010 &
1"
#12250980
0"
#12292650
b10010011 &
1"
#12334320
0"
#12375990
b10010100 &
1"
#12417660
0"
#12459330
b10010101 &
1"
#12501000
0"
#12542670
b10010110 &
1"
#12584340
0"
#12626010
b10010111 &
1"
#12667680
0"
#12709350
b10011000 &
1"
#12751020
0"
#12792690
b10011001 &
1"
#12834360
0"
#12876030
b10011010 &
1"
#12917700
0"
#12959370
b10011011 &
1"
#13001040
0"
#13042710
b10011100 &
1"
#13084380
0"
#13126050
b10011101 &
1"
#13167720
0"
#13209390
b10011110 &
1"
#13251060
0"
#13292730
b10011111 &
1"
#13334400
0"
#13376070
b10100000 &
1"
#13417740
0"
#13459410
b10100001 &
1"
#13501080
0"
#13542750
b10100010 &
1"
#13584420
0"
#13626090
b10100011 &
1"
#13667760
0"
#13709430
b10100100 &
1"
#13751100
0"
#13792770
b10100101 &
1"
#13834440
0"
#13876110
b10100110 &
1"
#13917780
0"
#13959450
b10100111 &
1"
#14001120
0"
#14042790
b10101000 &
1"
#14084460
0"
#14126130
b10101001 &
1"
#14167800
0"
#14209470
b10101010 &
1"
#14251140
0"
#14292810
b10101011 &
1"
#14334480
0"
#14376150
b10101100 &
1"
#14417820
0"
#14459490
b10101101 &
1"
#14501160
0"
#14542830
b10101110 &
1"
#14584500
0"
#14626170
b10101111 &
1"
#14667840
0"
#14709510
b10110000 &
1"
#14751180
0"
#14792850
b10110001 &
1"
#14834520
0"
#14876190
b10110010 &
1"
#14917860
0"
#14959530
b10110011 &
1"
#15001200
0"
#15042870
b10110100 &
1"
#15084540
0"
#15126210
b10110101 &
1"
#15167880
0"
#15209550
b10110110 &
1"
#15251220
0"
#15292890
b10110111 &
1"
#15334560
0"
#15376230
b10111000 &
1"
#15417900
0"
#15459570
b10111001 &
1"
#15501240
0"
#15542910
b10111010 &
1"
#15584580
0"
#15626250
b10111011 &
1"
#15667920
0"
#15709590
b10111100 &
1"
#15751260
0"
#15792930
b10111101 &
1"
#15834600
0"
#15876270
b10111110 &
1"
#15917940
0"
#15959610
b10111111 &
1"
#16001280
0"
#16042950
b11000000 &
1"
#16084620
0"
#16126290
b11000001 &
1"
#16167960
0"
#16209630
b11000010 &
1"
#16251300
0"
#16292970
b11000011 &
1"
#16334640
0"
#16376310
b11000100 &
1"
#16417980
0"
#16459650
b11000101 &
1"
#16501320
0"
#16542990
b11000110 &
1"
#16584660
0"
#16626330
b11000111 &
1"
#16668000
0"
#16709670
b11001000 &
1"
#16751340
0"
#16793010
b11001001 &
1"
#16834680
0"
#16876350
b11001010 &
1"
#16918020
0"
#16959690
b11001011 &
1"
#17001360
0"
#17043030
b11001100 &
1"
#17084700
0"
#17126370
b11001101 &
1"
#17168040
0"
#17209710
b11001110 &
1"
#17251380
0"
#17293050
b11001111 &
1"
#17334720
0"
#17376390
b11010000 &
1"
#17418060
0"
#17459730
b11010001 &
1"
#17501400
0"
#17543070
b11010010 &
1"
#17584740
0"
#17626410
b11010011 &
1"
#17668080
0"
#17709750
b11010100 &
1"
#17751420
0"
#17793090
b11010101 &
1"
#17834760
0"
#17876430
b11010110 &
1"
#17918100
0"
#17959770
b11010111 &
1"
#18001440
0"
#18043110
b11011000 &
1"
#18084780
0"
#18126450
b11011001 &
1"
#18168120
0"
#18209790
b11011010 &
1"
#18251460
0"
#18293130
b11011011 &
1"
#18334800
0"
#18376470
b11011100 &
1"
#18418140
0"
#18459810
b11011101 &
1"
#18501480
0"
#18543150
b11011110 &
1"
#18584820
0"
#18626490
b11011111 &
1"
#18668160
0"
#18709830
b11100000 &
1"
#18751500
0"
#18793170
b11100001 &
1"
#18834840
0"
#18876510
b11100010 &
1"
#18918180
0"
#18959850
b11100011 &
1"
#19001520
0"
#19043190
b11100100 &
1"
#19084860
0"
#19126530
b11100101 &
1"
#19168200
0"
#19209870
b11100110 &
1"
#19251540
0"
#19293210
b11100111 &
1"
#19334880
0"
#19376550
b11101000 &
1"
#19418220
0"
#19459890
b11101001 &
1"
#19501560
0"
#19543230
b11101010 &
1"
#19584900
0"
#19626570
b11101011 &
1"
#19668240
0"
#19709910
b11101100 &
1"
#19751580
0"
#19793250
b11101101 &
1"
#19834920
0"
#19876590
b11101110 &
1"
#19918260
0"
#19959930
b11101111 &
1"
#20001600
0"
#20043270
b11110000 &
1"
#20084940
0"
#20126610
b11110001 &
1"
#20168280
0"
#20209950
b11110010 &
1"
#20251620
0"
#20293290
b11110011 &
1"
#20334960
0"
#20376630
b11110100 &
1"
#20418300
0"
#20459970
b11110101 &
1"
#20501640
0"
#20543310
b11110110 &
1"
#20584980
0"
#20626650
b11110111 &
1"
#20668320
0"
#20709990
b11111000 &
1"
#20751660
0"
#20793330
b11111001 &
1"
#20835000
0"
#20876670
b11111010 &
1"
#20918340
0"
#20960010
b11111011 &
1"
#21001680
0"
#21043350
b11111100 &
1"
#21085020
0"
#21126690
b11111101 &
1"
#21168360
0"
#21210030
b11111110 &
1"
#21251700
0"
#21293370
b11111111 &
1"
#21335040
0"
#21376710
b100000000 &
1"
#21418380
0"
#21460050
b100000001 &
1"
#21501720
0"
#21543390
b100000010 &
1"
#21585060
0"
#21626730
b100000011 &
1"
#21668400
0"
#21710070
b100000100 &
1"
#21751740
0"
#21793410
b100000101 &
1"
#21835080
0"
#21876750
b100000110 &
1"
#21918420
0"
#21960090
b100000111 &
1"
#22001760
0"
#22043430
b100001000 &
1"
#22085100
0"
#22126770
b100001001 &
1"
#22168440
0"
#22210110
b100001010 &
1"
#22251780
0"
#22293450
b100001011 &
1"
#22335120
0"
#22376790
b100001100 &
1"
#22418460
0"
#22460130
b100001101 &
1"
#22501800
0"
#22543470
b100001110 &
1"
#22585140
0"
#22626810
b100001111 &
1"
#22668480
0"
#22710150
b100010000 &
1"
#22751820
0"
#22793490
b100010001 &
1"
#22835160
0"
#22876830
b100010010 &
1"
#22918500
0"
#22960170
b100010011 &
1"
#23001840
0"
#23043510
b100010100 &
1"
#23085180
0"
#23126850
b100010101 &
1"
#23168520
0"
#23210190
b100010110 &
1"
#23251860
0"
#23293530
b100010111 &
1"
#23335200
0"
#23376870
b100011000 &
1"
#23418540
0"
#23460210
b100011001 &
1"
#23501880
0"
#23543550
b100011010 &
1"
#23585220
0"
#23626890
b100011011 &
1"
#23668560
0"
#23710230
b100011100 &
1"
#23751900
0"
#23793570
b100011101 &
1"
#23835240
0"
#23876910
b100011110 &
1"
#23918580
0"
#23960250
b100011111 &
1"
#24001920
0"
#24043590
b100100000 &
1"
#24085260
0"
#24126930
b100100001 &
1"
#24168600
0"
#24210270
b100100010 &
1"
#24251940
0"
#24293610
b100100011 &
1"
#24335280
0"
#24376950
b100100100 &
1"
#24418620
0"
#24460290
b100100101 &
1"
#24501960
0"
#24543630
b100100110 &
1"
#24585300
0"
#24626970
b100100111 &
1"
#24668640
0"
#24710310
b100101000 &
1"
#24751980
0"
#24793650
b100101001 &
1"
#24835320
0"
#24876990
b100101010 &
1"
#24918660
0"
#24960330
b100101011 &
1"
#25002000
0"
#25043670
b100101100 &
1"
#25085340
0"
#25127010
b100101101 &
1"
#25168680
0"
#25210350
b100101110 &
1"
#25252020
0"
#25293690
b100101111 &
1"
#25335360
0"
#25377030
b100110000 &
1"
#25418700
0"
#25460370
b100110001 &
1"
#25502040
0"
#25543710
b100110010 &
1"
#25585380
0"
#25627050
b100110011 &
1"
#25668720
0"
#25710390
b100110100 &
1"
#25752060
0"
#25793730
b100110101 &
1"
#25835400
0"
#25877070
b100110110 &
1"
#25918740
0"
#25960410
b100110111 &
1"
#26002080
0"
#26043750
b100111000 &
1"
#26085420
0"
#26127090
b100111001 &
1"
#26168760
0"
#26210430
b100111010 &
1"
#26252100
0"
#26293770
b100111011 &
1"
#26335440
0"
#26377110
b100111100 &
1"
#26418780
0"
#26460450
b100111101 &
1"
#26502120
0"
#26543790
b100111110 &
1"
#26585460
0"
#26627130
b100111111 &
1"
#26668800
0"
#26710470
b101000000 &
1"
#26752140
0"
#26793810
b101000001 &
1"
#26835480
0"
#26877150
b101000010 &
1"
#26918820
0"
#26960490
b101000011 &
1"
#27002160
0"
#27043830
b101000100 &
1"
#27085500
0"
#27127170
b101000101 &
1"
#27168840
0"
#27210510
b101000110 &
1"
#27252180
0"
#27293850
b101000111 &
1"
#27335520
0"
#27377190
b101001000 &
1"
#27418860
0"
#27460530
b101001001 &
1"
#27502200
0"
#27543870
b101001010 &
1"
#27585540
0"
#27627210
b101001011 &
1"
#27668880
0"
#27710550
b101001100 &
1"
#27752220
0"
#27793890
b101001101 &
1"
#27835560
0"
#27877230
b101001110 &
1"
#27918900
0"
#27960570
b101001111 &
1"
#28002240
0"
#28043910
b101010000 &
1"
#28085580
0"
#28127250
b101010001 &
1"
#28168920
0"
#28210590
b101010010 &
1"
#28252260
0"
#28293930
b101010011 &
1"
#28335600
0"
#28377270
b101010100 &
1"
#28418940
0"
#28460610
b101010101 &
1"
#28502280
0"
#28543950
b101010110 &
1"
#28585620
0"
#28627290
b101010111 &
1"
#28668960
0"
#28710630
b101011000 &
1"
#28752300
0"
#28793970
b101011001 &
1"
#28835640
0"
#28877310
b101011010 &
1"
#28918980
0"
#28960650
b101011011 &
1"
#29002320
0"
#29043990
b101011100 &
1"
#29085660
0"
#29127330
b101011101 &
1"
#29169000
0"
#29210670
b101011110 &
1"
#29252340
0"
#29294010
b101011111 &
1"
#29335680
0"
#29377350
b101100000 &
1"
#29419020
0"
#29460690
b101100001 &
1"
#29502360
0"
#29544030
b101100010 &
1"
#29585700
0"
#29627370
b101100011 &
1"
#29669040
0"
#29710710
b101100100 &
1"
#29752380
0"
#29794050
b101100101 &
1"
#29835720
0"
#29877390
b101100110 &
1"
#29919060
0"
#29960730
b101100111 &
1"
#30002400
0"
#30044070
b101101000 &
1"
#30085740
0"
#30127410
b101101001 &
1"
#30169080
0"
#30210750
b101101010 &
1"
#30252420
0"
#30294090
b101101011 &
1"
#30335760
0"
#30377430
b101101100 &
1"
#30419100
0"
#30460770
b101101101 &
1"
#30502440
0"
#30544110
b101101110 &
1"
#30585780
0"
#30627450
b101101111 &
1"
#30669120
0"
#30710790
b101110000 &
1"
#30752460
0"
#30794130
b101110001 &
1"
#30835800
0"
#30877470
b101110010 &
1"
#30919140
0"
#30960810
b101110011 &
1"
#31002480
0"
#31044150
b101110100 &
1"
#31085820
0"
#31127490
b101110101 &
1"
#31169160
0"
#31210830
b101110110 &
1"
#31252500
0"
#31294170
b101110111 &
1"
#31335840
0"
#31377510
b101111000 &
1"
#31419180
0"
#31460850
b101111001 &
1"
#31502520
0"
#31544190
b101111010 &
1"
#31585860
0"
#31627530
b101111011 &
1"
#31669200
0"
#31710870
b101111100 &
1"
#31752540
0"
#31794210
b101111101 &
1"
#31835880
0"
#31877550
b101111110 &
1"
#31919220
0"
#31960890
b101111111 &
1"
#32002560
0"
#32044230
b110000000 &
1"
#32085900
0"
#32127570
b110000001 &
1"
#32169240
0"
#32210910
b110000010 &
1"
#32252580
0"
#32294250
b110000011 &
1"
#32335920
0"
#32377590
b110000100 &
1"
#32419260
0"
#32460930
b110000101 &
1"
#32502600
0"
#32544270
b110000110 &
1"
#32585940
0"
#32627610
b110000111 &
1"
#32669280
0"
#32710950
b110001000 &
1"
#32752620
0"
#32794290
b110001001 &
1"
#32835960
0"
#32877630
b110001010 &
1"
#32919300
0"
#32960970
b110001011 &
1"
#33002640
0"
#33044310
b110001100 &
1"
#33085980
0"
#33127650
b110001101 &
1"
#33169320
0"
#33210990
b110001110 &
1"
#33252660
0"
#33294330
b110001111 &
1"
#33336000
0"
#33377670
b110010000 &
1"
#33419340
0"
#33461010
b110010001 &
1"
#33502680
0"
#33544350
b110010010 &
1"
#33586020
0"
#33627690
b110010011 &
1"
#33669360
0"
#33711030
b110010100 &
1"
#33752700
0"
#33794370
b110010101 &
1"
#33836040
0"
#33877710
b110010110 &
1"
#33919380
0"
#33961050
b110010111 &
1"
#34002720
0"
#34044390
b110011000 &
1"
#34086060
0"
#34127730
b110011001 &
1"
#34169400
0"
#34211070
b110011010 &
1"
#34252740
0"
#34294410
b110011011 &
1"
#34336080
0"
#34377750
b110011100 &
1"
#34419420
0"
#34461090
b110011101 &
1"
#34502760
0"
#34544430
b110011110 &
1"
#34586100
0"
#34627770
b110011111 &
1"
#34669440
0"
#34711110
b110100000 &
1"
#34752780
0"
#34794450
b110100001 &
1"
#34836120
0"
#34877790
b110100010 &
1"
#34919460
0"
#34961130
b110100011 &
1"
#35002800
0"
#35044470
b110100100 &
1"
#35086140
0"
#35127810
b110100101 &
1"
#35169480
0"
#35211150
b110100110 &
1"
#35252820
0"
#35294490
b110100111 &
1"
#35336160
0"
#35377830
b110101000 &
1"
#35419500
0"
#35461170
b110101001 &
1"
#35502840
0"
#35544510
b110101010 &
1"
#35586180
0"
#35627850
b110101011 &
1"
#35669520
0"
#35711190
b110101100 &
1"
#35752860
0"
#35794530
b110101101 &
1"
#35836200
0"
#35877870
b110101110 &
1"
#35919540
0"
#35961210
b110101111 &
1"
#36002880
0"
#36044550
b110110000 &
1"
#36086220
0"
#36127890
b110110001 &
1"
#36169560
0"
#36211230
b110110010 &
1"
#36252900
0"
#36294570
b110110011 &
1"
#36336240
0"
#36377910
b110110100 &
1"
#36419580
0"
#36461250
b110110101 &
1"
#36502920
0"
#36544590
b110110110 &
1"
#36586260
0"
#36627930
b110110111 &
1"
#36669600
0"
#36711270
b110111000 &
1"
#36752940
0"
#36794610
b110111001 &
1"
#36836280
0"
#36877950
b110111010 &
1"
#36919620
0"
#36961290
b110111011 &
1"
#37002960
0"
#37044630
b110111100 &
1"
#37086300
0"
#37127970
b110111101 &
1"
#37169640
0"
#37211310
b110111110 &
1"
#37252980
0"
#37294650
b110111111 &
1"
#37336320
0"
#37377990
b111000000 &
1"
#37419660
0"
#37461330
b111000001 &
1"
#37503000
0"
#37544670
b111000010 &
1"
#37586340
0"
#37628010
b111000011 &
1"
#37669680
0"
#37711350
b111000100 &
1"
#37753020
0"
#37794690
b111000101 &
1"
#37836360
0"
#37878030
b111000110 &
1"
#37919700
0"
#37961370
b111000111 &
1"
#38003040
0"
#38044710
b111001000 &
1"
#38086380
0"
#38128050
b111001001 &
1"
#38169720
0"
#38211390
b111001010 &
1"
#38253060
0"
#38294730
b111001011 &
1"
#38336400
0"
#38378070
b111001100 &
1"
#38419740
0"
#38461410
b111001101 &
1"
#38503080
0"
#38544750
b111001110 &
1"
#38586420
0"
#38628090
b111001111 &
1"
#38669760
0"
#38711430
b111010000 &
1"
#38753100
0"
#38794770
b111010001 &
1"
#38836440
0"
#38878110
b111010010 &
1"
#38919780
0"
#38961450
b111010011 &
1"
#39003120
0"
#39044790
b111010100 &
1"
#39086460
0"
#39128130
b111010101 &
1"
#39169800
0"
#39211470
b111010110 &
1"
#39253140
0"
#39294810
b111010111 &
1"
#39336480
0"
#39378150
b111011000 &
1"
#39419820
0"
#39461490
b111011001 &
1"
#39503160
0"
#39544830
b111011010 &
1"
#39586500
0"
#39628170
b111011011 &
1"
#39669840
0"
#39711510
b111011100 &
1"
#39753180
0"
#39794850
b111011101 &
1"
#39836520
0"
#39878190
b111011110 &
1"
#39919860
0"
#39961530
b111011111 &
1"
#40003200
0"
#40044870
b111100000 &
1"
#40086540
0"
#40128210
b111100001 &
1"
#40169880
0"
#40211550
b111100010 &
1"
#40253220
0"
#40294890
b111100011 &
1"
#40336560
0"
#40378230
b111100100 &
1"
#40419900
0"
#40461570
b111100101 &
1"
#40503240
0"
#40544910
b111100110 &
1"
#40586580
0"
#40628250
b111100111 &
1"
#40669920
0"
#40711590
b111101000 &
1"
#40753260
0"
#40794930
b111101001 &
1"
#40836600
0"
#40878270
b111101010 &
1"
#40919940
0"
#40961610
b111101011 &
1"
#41003280
0"
#41044950
b111101100 &
1"
#41086620
0"
#41128290
b111101101 &
1"
#41169960
0"
#41211630
b111101110 &
1"
#41253300
0"
#41294970
b111101111 &
1"
#41336640
0"
#41378310
b111110000 &
1"
#41419980
0"
#41461650
b111110001 &
1"
#41503320
0"
#41544990
b111110010 &
1"
#41586660
0"
#41628330
b111110011 &
1"
#41670000
0"
#41711670
b111110100 &
1"
#41753340
0"
#41795010
b111110101 &
1"
#41836680
0"
#41878350
b111110110 &
1"
#41920020
0"
#41961690
b111110111 &
1"
#42003360
0"
#42045030
b111111000 &
1"
#42086700
0"
#42128370
b111111001 &
1"
#42170040
0"
#42211710
b111111010 &
1"
#42253380
0"
#42295050
b111111011 &
1"
#42336720
0"
#42378390
b111111100 &
1"
#42420060
0"
#42461730
b111111101 &
1"
#42503400
0"
#42545070
b111111110 &
1"
#42586740
0"
#42628410
b111111111 &
1"
#42670080
0"
#42711750
b1000000000 &
1"
#42753420
0"
#42795090
b1000000001 &
1"
#42836760
0"
#42878430
b1000000010 &
1"
#42920100
0"
#42961770
b1000000011 &
1"
#43003440
0"
#43045110
b1000000100 &
1"
#43086780
0"
#43128450
b1000000101 &
1"
#43170120
0"
#43211790
b1000000110 &
1"
#43253460
0"
#43295130
b1000000111 &
1"
#43336800
0"
#43378470
b1000001000 &
1"
#43420140
0"
#43461810
b1000001001 &
1"
#43503480
0"
#43545150
b1000001010 &
1"
#43586820
0"
#43628490
b1000001011 &
1"
#43670160
0"
#43711830
b1000001100 &
1"
#43753500
0"
#43795170
b1000001101 &
1"
#43836840
0"
#43878510
b1000001110 &
1"
#43920180
0"
#43961850
b1000001111 &
1"
#44003520
0"
#44045190
b1000010000 &
1"
#44086860
0"
#44128530
b1000010001 &
1"
#44170200
0"
#44211870
b1000010010 &
1"
#44253540
0"
#44295210
b1000010011 &
1"
#44336880
0"
#44378550
b1000010100 &
1"
#44420220
0"
#44461890
b1000010101 &
1"
#44503560
0"
#44545230
b1000010110 &
1"
#44586900
0"
#44628570
b1000010111 &
1"
#44670240
0"
#44711910
b1000011000 &
1"
#44753580
0"
#44795250
b1000011001 &
1"
#44836920
0"
#44878590
b1000011010 &
1"
#44920260
0"
#44961930
b1000011011 &
1"
#45003600
0"
#45045270
b1000011100 &
1"
#45086940
0"
#45128610
b1000011101 &
1"
#45170280
0"
#45211950
b1000011110 &
1"
#45253620
0"
#45295290
b1000011111 &
1"
#45336960
0"
#45378630
b1000100000 &
1"
#45420300
0"
#45461970
b1000100001 &
1"
#45503640
0"
#45545310
b1000100010 &
1"
#45586980
0"
#45628650
b1000100011 &
1"
#45670320
0"
#45711990
b1000100100 &
1"
#45753660
0"
#45795330
b1000100101 &
1"
#45837000
0"
#45878670
b1000100110 &
1"
#45920340
0"
#45962010
b1000100111 &
1"
#46003680
0"
#46045350
b1000101000 &
1"
#46087020
0"
#46128690
b1000101001 &
1"
#46170360
0"
#46212030
b1000101010 &
1"
#46253700
0"
#46295370
b1000101011 &
1"
#46337040
0"
#46378710
b1000101100 &
1"
#46420380
0"
#46462050
b1000101101 &
1"
#46503720
0"
#46545390
b1000101110 &
1"
#46587060
0"
#46628730
b1000101111 &
1"
#46670400
0"
#46712070
b1000110000 &
1"
#46753740
0"
#46795410
b1000110001 &
1"
#46837080
0"
#46878750
b1000110010 &
1"
#46920420
0"
#46962090
b1000110011 &
1"
#47003760
0"
#47045430
b1000110100 &
1"
#47087100
0"
#47128770
b1000110101 &
1"
#47170440
0"
#47212110
b1000110110 &
1"
#47253780
0"
#47295450
b1000110111 &
1"
#47337120
0"
#47378790
b1000111000 &
1"
#47420460
0"
#47462130
b1000111001 &
1"
#47503800
0"
#47545470
b1000111010 &
1"
#47587140
0"
#47628810
b1000111011 &
1"
#47670480
0"
#47712150
b1000111100 &
1"
#47753820
0"
#47795490
b1000111101 &
1"
#47837160
0"
#47878830
b1000111110 &
1"
#47920500
0"
#47962170
b1000111111 &
1"
#48003840
0"
#48045510
b1001000000 &
1"
#48087180
0"
#48128850
b1001000001 &
1"
#48170520
0"
#48212190
b1001000010 &
1"
#48253860
0"
#48295530
b1001000011 &
1"
#48337200
0"
#48378870
b1001000100 &
1"
#48420540
0"
#48462210
b1001000101 &
1"
#48503880
0"
#48545550
b1001000110 &
1"
#48587220
0"
#48628890
b1001000111 &
1"
#48670560
0"
#48712230
b1001001000 &
1"
#48753900
0"
#48795570
b1001001001 &
1"
#48837240
0"
#48878910
b1001001010 &
1"
#48920580
0"
#48962250
b1001001011 &
1"
#49003920
0"
#49045590
b1001001100 &
1"
#49087260
0"
#49128930
b1001001101 &
1"
#49170600
0"
#49212270
b1001001110 &
1"
#49253940
0"
#49295610
b1001001111 &
1"
#49337280
0"
#49378950
b1001010000 &
1"
#49420620
0"
#49462290
b1001010001 &
1"
#49503960
0"
#49545630
b1001010010 &
1"
#49587300
0"
#49628970
b1001010011 &
1"
#49670640
0"
#49712310
b1001010100 &
1"
#49753980
0"
#49795650
b1001010101 &
1"
#49837320
0"
#49878990
b1001010110 &
1"
#49920660
0"
